debugtoolkit/__init__.py
debugtoolkit/decorators.py
debugtoolkit-0.1.dist-info/LICENSE.txt
debugtoolkit-0.1.dist-info/METADATA
debugtoolkit-0.1.dist-info/WHEEL
debugtoolkit-0.1.dist-info/top_level.txt
debugtoolkit-0.1.dist-info/RECORD
