Metadata-Version: 2.1
Name: debugtoolkit
Version: 0.1
Summary: DebugToolkit is a versatile Python package designed for debugging
Home-page: https://github.com/andrijdavid/python-debugtoolkit/
Author: Andrij David
Author-email: david@geek.mg
License: BSD-2-Clause
Project-URL: Documentation, https://python-debugtoolkit.readthedocs.io
Project-URL: Source, https://github.com/andrijdavid/python-debugtoolkit
Project-URL: Tracker, https://github.com/pyscaffold/pyscaffold/issues
Project-URL: Download, https://pypi.org/project/debugtoolkit/#files
Platform: any
Classifier: Development Status :: 4 - Beta
Classifier: Programming Language :: Python
Classifier: Programming Language :: Python :: 3
Classifier: Intended Audience :: Developers
Classifier: License :: OSI Approved :: MIT License
Classifier: Operating System :: POSIX :: Linux
Classifier: Operating System :: Unix
Classifier: Operating System :: MacOS
Classifier: Operating System :: Microsoft :: Windows
License-File: LICENSE.txt
Requires-Dist: psutil
Requires-Dist: importlib-metadata ; python_version < "3.8"
Provides-Extra: testing
Requires-Dist: setuptools ; extra == 'testing'
Requires-Dist: pytest ; extra == 'testing'
Requires-Dist: pytest-cov ; extra == 'testing'
